ctx_bandits_mcmc-1.0.1.dist-info/licenses/LICENSE
src/MCMC.py
src/__init__.py
src/baseline.py
src/dataset.py
src/game.py
src/toy_example.py
ctx_bandits_mcmc-1.0.1.dist-info/METADATA
ctx_bandits_mcmc-1.0.1.dist-info/WHEEL
ctx_bandits_mcmc-1.0.1.dist-info/entry_points.txt
ctx_bandits_mcmc-1.0.1.dist-info/top_level.txt
ctx_bandits_mcmc-1.0.1.dist-info/RECORD
