Metadata-Version: 2.4
Name: ctx-bandits-mcmc
Version: 1.0.1
Summary: Feel-Good Thompson Sampling for Contextual Bandits: a Markov Chain Monte Carlo Showdown
Home-page: https://github.com/SarahLiaw/ctx-bandits-mcmc-showdown
Author: Emile Anand, Sarah Liaw
Author-email: emiletimothy@outlook.com
License: MIT
Project-URL: Homepage, https://github.com/SarahLiaw/ctx-bandits-mcmc-showdown
Project-URL: Documentation, https://github.com/SarahLiaw/ctx-bandits-mcmc-showdown/README.md
Project-URL: Repository, https://github.com/SarahLiaw/ctx-bandits-mcmc-showdown
Project-URL: Paper, https://arxiv.org/abs/2507.15290
Keywords: thompson-sampling,contextual-bandits,mcmc,reinforcement-learning,bayesian
Classifier: Development Status :: 4 - Beta
Classifier: Intended Audience :: Science/Research
Classifier: Topic :: Scientific/Engineering :: Artificial Intelligence
Classifier: License :: OSI Approved :: MIT License
Classifier: Programming Language :: Python :: 3
Classifier: Programming Language :: Python :: 3.8
Classifier: Programming Language :: Python :: 3.9
Classifier: Programming Language :: Python :: 3.10
Classifier: Programming Language :: Python :: 3.11
Requires-Python: >=3.8
License-File: LICENSE
Requires-Dist: torch>=2.0.0
Requires-Dist: numpy>=1.20.0
Requires-Dist: matplotlib>=3.0.0
Requires-Dist: scipy>=1.10.0
Requires-Dist: pandas>=1.0.0
Requires-Dist: scikit-learn>=1.0.0
Requires-Dist: tqdm>=4.60.0
Requires-Dist: wandb>=0.12.0
Requires-Dist: pytest>=7.0.0
Requires-Dist: pydantic>=2.0.0
Requires-Dist: PyYAML>=6.0.0
Provides-Extra: dev
Requires-Dist: pytest>=7.0.0; extra == "dev"
Requires-Dist: pytest-cov>=3.0.0; extra == "dev"
Requires-Dist: black>=22.0.0; extra == "dev"
Requires-Dist: flake8>=4.0.0; extra == "dev"
Requires-Dist: mypy>=0.950; extra == "dev"
Requires-Dist: build>=0.10.0; extra == "dev"
Requires-Dist: twine>=4.0.0; extra == "dev"
Provides-Extra: neural
Requires-Dist: yfinance; extra == "neural"
Requires-Dist: xlrd>=2.0.0; extra == "neural"
Dynamic: author-email
Dynamic: home-page
Dynamic: license-file
Dynamic: requires-python
